dice/__init__.py
dice/__main__.py
dice/command.py
dice/constants.py
dice/elements.py
dice/exceptions.py
dice/grammar.py
dice/utilities.py
dice/tests/__init__.py
dice/tests/conftest.py
dice/tests/test_command.py
dice/tests/test_elements.py
dice/tests/test_grammar.py
dice/tests/test_utilities.py
dice-3.1.2.dist-info/LICENCE
dice-3.1.2.dist-info/METADATA
dice-3.1.2.dist-info/WHEEL
dice-3.1.2.dist-info/entry_points.txt
dice-3.1.2.dist-info/top_level.txt
dice-3.1.2.dist-info/RECORD
