Metadata-Version: 1.1
Name: dice
Version: 3.1.2
Summary: A library for parsing and evaluating dice notation
Home-page: https://github.com/borntyping/python-dice
Author: Sam Clements
Author-email: sam@borntyping.co.uk
License: MIT
Platform: UNKNOWN
Classifier: Development Status :: 5 - Production/Stable
Classifier: Environment :: Console
Classifier: Intended Audience :: Developers
Classifier: Intended Audience :: Other Audience
Classifier: License :: OSI Approved :: MIT License
Classifier: Operating System :: OS Independent
Classifier: Programming Language :: Python
Classifier: Programming Language :: Python :: 3
Classifier: Programming Language :: Python :: 3.6
Classifier: Programming Language :: Python :: 3.7
Classifier: Programming Language :: Python :: 3.8
Classifier: Programming Language :: Python :: 3.9
Classifier: Topic :: Games/Entertainment
Classifier: Topic :: Games/Entertainment :: Board Games
Classifier: Topic :: Games/Entertainment :: Role-Playing
Classifier: Topic :: Games/Entertainment :: Multi-User Dungeons (MUD)
Classifier: Topic :: Games/Entertainment :: Turn Based Strategy
Classifier: Topic :: Utilities
